{
    "1": {
        "_id": 1,
        "_date": "Thu Jan 11 2024",
        "_timestamp": 1705037125086,
        "description": "normalization",
        "isStarred": false,
        "boards": [
            "@now"
        ],
        "_isTask": true,
        "isComplete": false,
        "inProgress": false,
        "priority": 1
    },
    "2": {
        "_id": 2,
        "_date": "Thu Jan 11 2024",
        "_timestamp": 1705037139215,
        "description": "rbac",
        "isStarred": false,
        "boards": [
            "@now"
        ],
        "_isTask": true,
        "isComplete": false,
        "inProgress": false,
        "priority": 1
    },
    "3": {
        "_id": 3,
        "_date": "Thu Jan 11 2024",
        "_timestamp": 1705037165128,
        "description": "authn/o",
        "isStarred": false,
        "boards": [
            "@now"
        ],
        "_isTask": true,
        "isComplete": false,
        "inProgress": false,
        "priority": 1
    },
    "4": {
        "_id": 4,
        "_date": "Thu Jan 11 2024",
        "_timestamp": 1705037181210,
        "description": "jessica",
        "isStarred": false,
        "boards": [
            "@now"
        ],
        "_isTask": true,
        "isComplete": false,
        "inProgress": false,
        "priority": 1
    },
    "5": {
        "_id": 5,
        "_date": "Thu Jan 11 2024",
        "_timestamp": 1705037200161,
        "description": "events",
        "isStarred": false,
        "boards": [
            "@now"
        ],
        "_isTask": true,
        "isComplete": false,
        "inProgress": false,
        "priority": 1
    },
    "6": {
        "_id": 6,
        "_date": "Fri Jan 12 2024",
        "_timestamp": 1705074833834,
        "description": "routes with actions",
        "isStarred": false,
        "boards": [
            "@now"
        ],
        "_isTask": true,
        "isComplete": false,
        "inProgress": false,
        "priority": 1
    },
    "7": {
        "_id": 7,
        "_date": "Fri Jan 12 2024",
        "_timestamp": 1705074852342,
        "description": "6 THINGS TO WORK ON TOGETHER",
        "isStarred": false,
        "boards": [
            "@now"
        ],
        "_isTask": false
    },
    "9": {
        "_id": 9,
        "_date": "Fri Jan 12 2024",
        "_timestamp": 1705074948540,
        "description": "1. SLOW & COMPLETE",
        "isStarred": false,
        "boards": [
            "@now"
        ],
        "_isTask": false
    },
    "10": {
        "_id": 10,
        "_date": "Fri Jan 12 2024",
        "_timestamp": 1705074985309,
        "description": "2. ASK FOR LESS",
        "isStarred": false,
        "boards": [
            "@now"
        ],
        "_isTask": false
    },
    "11": {
        "_id": 11,
        "_date": "Fri Jan 12 2024",
        "_timestamp": 1705074999661,
        "description": "3. DO MORE",
        "isStarred": false,
        "boards": [
            "@now"
        ],
        "_isTask": false
    },
    "12": {
        "_id": 12,
        "_date": "Fri Jan 12 2024",
        "_timestamp": 1705075210982,
        "description": "add secrets",
        "isStarred": false,
        "boards": [
            "@todo"
        ],
        "_isTask": true,
        "isComplete": false,
        "inProgress": true,
        "priority": 1
    }
}